hipnuc_usb_apiserver/Config.py
hipnuc_usb_apiserver/__init__.py
hipnuc_usb_apiserver/__main__.py
hipnuc_usb_apiserver/apiserver/__init__.py
hipnuc_usb_apiserver/apiserver/app.py
hipnuc_usb_apiserver/apiserver/main.py
hipnuc_usb_apiserver/apiserver/server.py
hipnuc_usb_apiserver/client/__init__.py
hipnuc_usb_apiserver/cmd/__init__.py
hipnuc_usb_apiserver/cmd/configure.py
hipnuc_usb_apiserver/grpc/__init__.py
hipnuc_usb_apiserver/grpc/imu_packet_pb2.py
hipnuc_usb_apiserver/grpc/imu_packet_pb2_grpc.py
hipnuc_usb_apiserver/hipnuc/__init__.py
hipnuc_usb_apiserver/hipnuc/demo.py
hipnuc_usb_apiserver/hipnuc/hipnuc_module.py
hipnuc_usb_apiserver/hipnuc/hipnuc_protocol.py
hipnuc_usb_apiserver-0.3.0.dist-info/METADATA
hipnuc_usb_apiserver-0.3.0.dist-info/WHEEL
hipnuc_usb_apiserver-0.3.0.dist-info/top_level.txt
hipnuc_usb_apiserver-0.3.0.dist-info/RECORD
