Metadata-Version: 2.1
Name: hipnuc-usb-apiserver
Version: 0.3.0
Summary: Driver for Arizona USB Pressure Sensor
Author: davidliyutong
Author-email: davidliyutong@sjtu.edu.cn
Requires-Python: >=3.7
Requires-Dist: grpcio
Requires-Dist: grpcio-tools
Requires-Dist: markit-tcpbroker
Requires-Dist: pyyaml
